{
  "rasa_nlu_data": {
    "common_examples": [
      {
        "intent": "products",
        "text": "What products can I buy?"
      },
      {
        "intent": "products",
        "text": "What products are available?"
      },
      {
        "intent": "products",
        "text": "What can I buy?"
      },
      {
        "intent": "products",
        "text": "What is available for purchase?"
      },
      {
        "intent": "products",
        "text": "What products do you have?"
      },
      {
        "intent": "shop",
        "text": "When is the shop open?"
      },
      {
        "intent": "shop",
        "text": "What is the shop timing?"
      },
      {
        "intent": "shop",
        "text": "When are you open?"
      },
      {
        "intent": "shop",
        "text": "When does the shop close?"
      },
      {
        "intent": "bot",
        "text": "Who are you?"
      },
      {
        "intent": "bot",
        "text": "Are you a bot?"
      },
      {
        "intent": "time",
        "text": "What is the time now?"
      },
      {
        "intent": "time",
        "text": "Can you tell me the time?"
      },
      {
        "intent": "date",
        "text": "What is the date today?"
      },
      {
        "intent": "date",
        "text": "Can you tell me the date today?"
      },
      {
        "intent": "date",
        "text": "Do you know today's date?"
      },
      {
        "intent": "greet",
        "text": "hey"
      },
      {
        "intent": "greet",
        "text": "hey"
      },
      {
        "intent": "greet",
        "text": "hey"
      },
      {
        "intent": "greet",
        "text": "hey"
      },
      {
        "intent": "greet",
        "text": "howdy"
      },
      {
        "intent": "greet",
        "text": "hello"
      },
      {
        "intent": "greet",
        "text": "hi"
      },
      {
        "entities": [
          {
            "start": 10,
            "entity": "query",
            "value": "goroutine",
            "end": 19
          }
        ],
        "intent": "whatis",
        "text": "What is a goroutine?"
      },
      {
        "entities": [
          {
            "start": 11,
            "entity": "query",
            "value": "president of Vietnam",
            "end": 31
          }
        ],
        "intent": "whatis",
        "text": "Who is the president of Vietnam?"
      },
      {
        "entities": [
          {
            "start": 8,
            "entity": "query",
            "value": "love",
            "end": 12
          }
        ],
        "intent": "whatis",
        "text": "What is love?"
      },
      {
        "entities": [
          {
            "start": 8,
            "entity": "query",
            "value": "dinosaurs",
            "end": 17
          }
        ],
        "intent": "whatis",
        "text": "Who are dinosaurs?"
      },
      {
        "entities": [
          {
            "start": 11,
            "entity": "query",
            "value": "eclipse",
            "end": 18
          }
        ],
        "intent": "whatis",
        "text": "What is an eclipse?"
      },
      {
        "entities": [
          {
            "start": 9,
            "entity": "query",
            "value": "christian",
            "end": 18
          }
        ],
        "intent": "whatis",
        "text": "Who is a christian?"
      },
      {
        "entities": [
          {
            "start": 10,
            "entity": "query",
            "value": "engineer",
            "end": 18
          }
        ],
        "intent": "whatis",
        "text": "Who is an engineer?"
      },
      {
        "entities": [
          {
            "start": 12,
            "entity": "query",
            "value": "population of Vietnam",
            "end": 33
          }
        ],
        "intent": "whatis",
        "text": "What is the population of Vietnam?"
      },
      {
        "entities": [
          {
            "start": 32,
            "entity": "query",
            "value": "Golang",
            "end": 38
          }
        ],
        "intent": "whatis",
        "text": "Can you tell me something about Golang?"
      },
      {
        "entities": [
          {
            "start": 19,
            "entity": "query",
            "value": "Riki",
            "end": 23
          }
        ],
        "intent": "whatis",
        "text": "Do you know who is Riki?"
      },
      {
        "entities": [
          {
            "start": 20,
            "entity": "query",
            "value": "OOP",
            "end": 23
          }
        ],
        "intent": "whatis",
        "text": "Do you know what is OOP?"
      },
      {
        "entities": [
          {
            "start": 20,
            "entity": "query",
            "value": "price of Bitcoin",
            "end": 36
          }
        ],
        "intent": "whatis",
        "text": "Can you give me the price of Bitcoin?"
      },
      {
        "entities": [
          {
            "start": 16,
            "entity": "query",
            "value": "USD VND rate",
            "end": 28
          }
        ],
        "intent": "whatis",
        "text": "Can you give me USD VND rate?"
      },
      {
        "entities": [
          {
            "start": 12,
            "entity": "query",
            "value": "meaning of life",
            "end": 27
          }
        ],
        "intent": "whatis",
        "text": "What is the meaning of life?"
      },
      {
        "entities": [
          {
            "start": 7,
            "entity": "query",
            "value": "John Lennon",
            "end": 18
          }
        ],
        "intent": "whatis",
        "text": "Who is John Lennon?"
      },
      {
        "entities": [
          {
            "start": 12,
            "entity": "query",
            "value": "biggest country in the world",
            "end": 40
          }
        ],
        "intent": "whatis",
        "text": "What is the biggest country in the world?"
      },
      {
        "entities": [
          {
            "start": 12,
            "entity": "query",
            "value": "most expensive food in the world",
            "end": 44
          }
        ],
        "intent": "whatis",
        "text": "What is the most expensive food in the world?"
      },
      {
        "entities": [
          {
            "start": 6,
            "entity": "query",
            "value": " boil eggs",
            "end": 16
          }
        ],
        "intent": "howto",
        "text": "How to boil eggs?"
      },
      {
        "entities": [
          {
            "start": 7,
            "entity": "query",
            "value": "practice yoga",
            "end": 20
          }
        ],
        "intent": "howto",
        "text": "How to practice yoga?"
      },
      {
        "entities": [
          {
            "start": 7,
            "entity": "query",
            "value": "learn programming",
            "end": 24
          }
        ],
        "intent": "howto",
        "text": "How to learn programming?"
      },
      {
        "entities": [
          {
            "start": 5,
            "entity": "query",
            "value": "John Lennon died",
            "end": 21
          }
        ],
        "intent": "when",
        "text": "When John Lennon died?"
      },
      {
        "entities": [
          {
            "start": 5,
            "entity": "query",
            "value": "Second World War started",
            "end": 29
          }
        ],
        "intent": "when",
        "text": "When Second World War started?"
      },
      {
        "entities": [
          {
            "start": 28,
            "entity": "query",
            "value": "Universe",
            "end": 36
          }
        ],
        "intent": "whatis",
        "text": "Can you tell me what is the Universe?"
      },
      {
        "entities": [
          {
            "start": 23,
            "entity": "query",
            "value": "Bismarck Lepe",
            "end": 36
          }
        ],
        "intent": "whatis",
        "text": "Can you tell me who is Bismarck Lepe?"
      },
      {
        "entities": [
          {
            "start": 3,
            "entity": "query",
            "value": "plants die of old age",
            "end": 24
          }
        ],
        "intent": "do",
        "text": "Do plants die of old age?"
      },
      {
        "entities": [
          {
            "start": 5,
            "entity": "query",
            "value": "chewing gum really stay inside you for years",
            "end": 49
          }
        ],
        "intent": "do",
        "text": "Does chewing gum really stay inside you for years?"
      },
      {
        "entities": [
          {
            "start": 20,
            "entity": "query",
            "value": "goroutine",
            "end": 29
          }
        ],
        "intent": "whatis",
        "text": "Do you know what is goroutine?"
      },
      {
        "entities": [
          {
            "start": 24,
            "entity": "query",
            "value": "goroutine",
            "end": 33
          }
        ],
        "intent": "whatis",
        "text": "Can you tell me what is goroutine?"
      },
      {
        "entities": [
          {
            "start": 3,
            "entity": "query",
            "value": "iphone 6",
            "end": 11
          }
        ],
        "intent": "is",
        "text": "Is iphone 6 available?"
      },
      {
        "entities": [
          {
            "start": 12,
            "entity": "query",
            "value": "iphone 6",
            "end": 20
          }
        ],
        "intent": "do",
        "text": "Do you have iphone 6?"
      },
      {
        "entities": [
          {
            "start": 12,
            "entity": "query",
            "value": "iphone 6",
            "end": 20
          }
        ],
        "intent": "do",
        "text": "Do you have iphone 6 in stock?"
      },
      {
        "entities": [
          {
            "start": 16,
            "entity": "query",
            "value": "iphone 6",
            "end": 24
          }
        ],
        "intent": "can",
        "text": "Can you show me iphone 6?"
      }
    ],
    "regex_features": [],
    "entity_synonyms": []
  }
}